[
    {
        "id":"1.",
        "name":"NFT Top Artist",
        "price":"8.6 ETH or $12,000"
    },
    {
        "id":"2.",
        "name":"George Brandon",
        "price":"4.8 ETH or $14,000"
    },
    {
        "id":"3.",
        "name":"Johnny Mayson",
        "price":"6.2 ETH or $26,000"
    },
    {
        "id":"4.",
        "name":"Liberty Artist",
        "price":"4.5 ETH or $11,600"
    },
    {
        "id":"5.",
        "name":"Ronald Martino",
        "price":"7.2 ETH or $14,500"
    },
    {
        "id":"6.",
        "name":"Anthony Brown",
        "price":"8.6 ETH or $7,400"
    },
    {
        "id":"7.",
        "name":"Liberty Artist",
        "price":"9.8 ETH or $14,200"
    },
    {
        "id":"8.",
        "name":"Ronald Martino",
        "price":"6.5 ETH or $15,000"
    },
    {
        "id":"9.",
        "name":"David Walker",
        "price":"2.5 ETH or $12,000"
    },
    {
        "id":"10.",
        "name":"Liberty Artist",
        "price":"8.8 ETH or $16,800"
    },
    {
        "id":"11.",
        "name":"Anthony Brown",
        "price":"7.5 ETH or $15,400"
    },
    {
        "id":"12.",
        "name":"David Walker",
        "price":"5.2 ETH or $12,300"
    }
]